mutwo/timeline_converters/__init__.py
mutwo/timeline_converters/timelines.py
mutwo/timeline_interfaces/__init__.py
mutwo/timeline_interfaces/timelines.py
mutwo/timeline_utilities/__init__.py
mutwo/timeline_utilities/exceptions.py
mutwo/timeline_version/__init__.py
mutwo.timeline-0.6.0.dist-info/LICENSE
mutwo.timeline-0.6.0.dist-info/METADATA
mutwo.timeline-0.6.0.dist-info/WHEEL
mutwo.timeline-0.6.0.dist-info/top_level.txt
mutwo.timeline-0.6.0.dist-info/RECORD
