Metadata-Version: 2.1
Name: mutwo.timeline
Version: 0.6.0
Summary: timeline extension for event based framework for generative art
Home-page: https://github.com/mutwo-org/mutwo.timeline
Author: Levin Eric Zimmermann
Author-email: levin.eric.zimmermann@posteo.eu
License: GPL
Project-URL: Documentation, https://mutwo-org.github.io
Requires-Python: >=3.10, <4
License-File: LICENSE
Requires-Dist: mutwo.core <3.0.0,>=2.0.0
Requires-Dist: python-ranges <2.0.0,>=1.2.0
Provides-Extra: testing
Requires-Dist: pytest >=7.1.1 ; extra == 'testing'
